gridnet/__init__.py
gridnet/exceptions.py
gridnet/gridnet.py
gridnet/models.py
gridnet/py.typed
gridnet-5.0.0.dist-info/LICENSE
gridnet-5.0.0.dist-info/METADATA
gridnet-5.0.0.dist-info/WHEEL
gridnet-5.0.0.dist-info/RECORD
