Metadata-Version: 2.1
Name: gridnet
Version: 5.0.0
Summary: Asynchronous Python client for a NET2GRID devices
Home-page: https://github.com/klaasnicolaas/python-gridnet
License: MIT
Keywords: net2grid,energy,device,power,async,client
Author: Klaas Schoute
Author-email: hello@student-techlife.com
Maintainer: Klaas Schoute
Maintainer-email: hello@student-techlife.com
Requires-Python: >=3.11,<4.0
Classifier: Development Status :: 5 - Production/Stable
Classifier: Framework :: AsyncIO
Classifier: Intended Audience :: Developers
Classifier: License :: OSI Approved :: MIT License
Classifier: Natural Language :: English
Classifier: Programming Language :: Python :: 3
Classifier: Programming Language :: Python :: 3.11
Classifier: Programming Language :: Python :: 3.12
Classifier: Topic :: Software Development :: Libraries :: Python Modules
Requires-Dist: aiohttp (>=3.0.0)
Requires-Dist: yarl (>=1.6.0)
Project-URL: Bug Tracker, https://github.com/klaasnicolaas/python-gridnet/issues
Project-URL: Changelog, https://github.com/klaasnicolaas/python-gridnet/releases
Project-URL: Documentation, https://github.com/klaasnicolaas/python-gridnet
Project-URL: Repository, https://github.com/klaasnicolaas/python-gridnet
